[{
        "menuId": 0,
        "primerPlato": "Sopa de verduras",
        "segundoPlato": "Hamburguesa de ternera",
        "postre": "Helado",
        "precio": 12,
        "isAvailable": true,
        "image": " "
    },

    {
        "menuId": 1,
        "primerPlato": "Espaguetis a la carbonara",
        "segundoPlato": "Tortilla Francesa",
        "postre": "Tarta de queso",
        "precio": 15,
        "isAvailable": true,
        "image": " "
    },

    {
        "menuId": 2,
        "primerPlato": "Sopa de Cocido",
        "segundoPlato": "Cocido Completo",
        "postre": "Tarta de manzana",
        "precio": 15,
        "isAvailable": true,
        "image": " "
    },

    {
        "menuId": 3,
        "primerPlato": "Arroz con pollo",
        "segundoPlato": "Nuggets de pollo",
        "postre": "Yogur griego",
        "precio": 10,
        "isAvailable": true,
        "image": " "
    },

    {
        "menuId": 4,
        "primerPlato": "Lentejas",
        "segundoPlato": "Hamburguesa de pollo",
        "postre": "Fresas con nata",
        "precio": 13,
        "isAvailable": true,
        "image": " "
    },

    {
        "menuId": 5,
        "primerPlato": "Gnochis con pesto",
        "segundoPlato": "Salmon al horno",
        "postre": "Mandarina",
        "precio": 16,
        "isAvailable": true,
        "image": " "
    },

    {
        "menuId": 6,
        "primerPlato": "Arroz con carabineros",
        "segundoPlato": "Filete de ternera",
        "postre": "Tarta de queso",
        "precio": 25,
        "isAvailable": true,
        "image": " "
    },

    {
        "menuId": 7,
        "primerPlato": "Risotto de setas",
        "segundoPlato": "Pizza",
        "postre": "Brownie con helado",
        "precio": 12,
        "isAvailable": true,
        "image": " "
    },

    {
        "menuId": 8,
        "primerPlato": "Pescado a la plancha",
        "segundoPlato": "Alitas de Pollo",
        "postre": "Pera",
        "precio": 10,
        "isAvailable": true,
        "image": " "
    },

    {
        "menuId": 9,
        "primerPlato": "Lasaña de carne",
        "segundoPlato": "Palomitas de pollo",
        "postre": "Tiramisu",
        "precio": 18,
        "isAvailable": true,
        "image": " "
    }

]